<?xml version="1.0" encoding="GBK"?>

<document>
  <items>
    <item>
      <hits>905</hits>
      <imgPath><![CDATA[http://vimg2.ws.126.net/image/snapshot/2014/3/G/C/V9N8J3OGC_120~90.jpg]]></imgPath>
      <pageUrl><![CDATA[http://v.mobile.163.com/video/2014/3/G/B/V9N8J3OGB.html]]></pageUrl>
      <playLength>89</playLength>
      <source><![CDATA[网易]]></source>
      <title><![CDATA[佟掌柜砖机 Jawbone UP24]]></title>
      <videoId><![CDATA[V9N8J3OGB]]></videoId>
    </item>
    <item>
      <hits>2156</hits>
      <imgPath><![CDATA[http://vimg1.ws.126.net/image/snapshot/2014/2/H/V/V9JF16UHV_120~90.jpg]]></imgPath>
      <pageUrl><![CDATA[http://v.mobile.163.com/video/2014/2/H/U/V9JF16UHU.html]]></pageUrl>
      <playLength>202</playLength>
      <source><![CDATA[网易]]></source>
      <title><![CDATA[佟掌柜砖机 春节逛庙会防丢利器]]></title>
      <videoId><![CDATA[V9JF16UHU]]></videoId>
    </item>
    <item>
      <hits>1995</hits>
      <imgPath><![CDATA[http://vimg1.ws.126.net/image/snapshot/2014/2/0/A/V9JEUST0A_120~90.jpg]]></imgPath>
      <pageUrl><![CDATA[http://v.mobile.163.com/video/2014/2/0/9/V9JEUST09.html]]></pageUrl>
      <playLength>958</playLength>
      <source><![CDATA[网易]]></source>
      <title><![CDATA[佟掌柜砖机 亲戚串门必备游戏]]></title>
      <videoId><![CDATA[V9JEUST09]]></videoId>
    </item>
    <item>
      <hits>828</hits>
      <imgPath><![CDATA[http://vimg3.ws.126.net/image/snapshot/2014/4/B/5/V9NTQIHB5_120~90.jpg]]></imgPath>
      <pageUrl><![CDATA[http://v.mobile.163.com/video/2014/4/B/4/V9NTQIHB4.html]]></pageUrl>
      <playLength>754</playLength>
      <source><![CDATA[网易]]></source>
      <title><![CDATA[佟掌柜砖机第二十五期 Jawbone UP24 视频评测]]></title>
      <videoId><![CDATA[V9NTQIHB4]]></videoId>
    </item>
    <item>
      <hits>744</hits>
      <imgPath><![CDATA[http://vimg3.ws.126.net/image/snapshot/2013/11/S/H/V9CN2APSH_120~90.jpg]]></imgPath>
      <pageUrl><![CDATA[http://v.mobile.163.com/video/2013/11/S/G/V9CN2APSG.html]]></pageUrl>
      <playLength>120</playLength>
      <source><![CDATA[网易]]></source>
      <title><![CDATA[佟掌柜砖机第十六期 galaring智能戒指]]></title>
      <videoId><![CDATA[V9CN2APSG]]></videoId>
    </item>
    <item>
      <hits>302</hits>
      <imgPath><![CDATA[http://vimg2.ws.126.net/image/snapshot/2014/2/8/6/V9JSCBG86_120~90.jpg]]></imgPath>
      <pageUrl><![CDATA[http://v.mobile.163.com/video/2014/2/8/5/V9JSCBG85.html]]></pageUrl>
      <playLength>200</playLength>
      <source><![CDATA[网易]]></source>
      <title><![CDATA[佟掌柜砖机 节后减肥必备神器]]></title>
      <videoId><![CDATA[V9JSCBG85]]></videoId>
    </item>
    <item>
      <hits>103</hits>
      <imgPath><![CDATA[http://vimg2.ws.126.net/image/snapshot/2013/11/U/M/V9CNM6NUM_120~90.jpg]]></imgPath>
      <pageUrl><![CDATA[http://v.mobile.163.com/video/2013/11/U/L/V9CNM6NUL.html]]></pageUrl>
      <playLength>264</playLength>
      <source><![CDATA[网易]]></source>
      <title><![CDATA[佟掌柜砖机第十六期 BlueBerry]]></title>
      <videoId><![CDATA[V9CNM6NUL]]></videoId>
    </item>
    <item>
      <hits>1038</hits>
      <imgPath><![CDATA[http://vimg3.ws.126.net/image/snapshot/2014/1/5/G/V9HBBQP5G_120~90.jpg]]></imgPath>
      <pageUrl><![CDATA[http://v.mobile.163.com/video/2014/1/5/F/V9HBBQP5F.html]]></pageUrl>
      <playLength>213</playLength>
      <source><![CDATA[网易]]></source>
      <title><![CDATA[佟掌柜砖机第二十一期 意念猫耳朵]]></title>
      <videoId><![CDATA[V9HBBQP5F]]></videoId>
    </item>
    <item>
      <hits>1445</hits>
      <imgPath><![CDATA[http://vimg2.ws.126.net/image/snapshot/2013/12/N/1/V9FHM32N1_120~90.jpg]]></imgPath>
      <pageUrl><![CDATA[http://v.mobile.163.com/video/2013/12/N/0/V9FHM32N0.html]]></pageUrl>
      <playLength>1546</playLength>
      <source><![CDATA[网易]]></source>
      <title><![CDATA[佟掌柜砖机第十八期 Xplay3S发布会]]></title>
      <videoId><![CDATA[V9FHM32N0]]></videoId>
    </item>
    <item>
      <hits>577</hits>
      <imgPath><![CDATA[http://vimg2.ws.126.net/image/snapshot/2013/11/4/R/V9CNPI54R_120~90.jpg]]></imgPath>
      <pageUrl><![CDATA[http://v.mobile.163.com/video/2013/11/4/Q/V9CNPI54Q.html]]></pageUrl>
      <playLength>133</playLength>
      <source><![CDATA[网易]]></source>
      <title><![CDATA[佟掌柜砖机第十六期 莱格威智能骑行设备]]></title>
      <videoId><![CDATA[V9CNPI54Q]]></videoId>
    </item>
    <item>
      <hits>115</hits>
      <imgPath><![CDATA[http://vimg3.ws.126.net/image/snapshot/2014/1/1/3/V9HB9CH13_120~90.jpg]]></imgPath>
      <pageUrl><![CDATA[http://v.mobile.163.com/video/2014/1/1/2/V9HB9CH12.html]]></pageUrl>
      <playLength>157</playLength>
      <source><![CDATA[网易]]></source>
      <title><![CDATA[佟掌柜砖机第二十一期 yeelight]]></title>
      <videoId><![CDATA[V9HB9CH12]]></videoId>
    </item>
    <item>
      <hits>69</hits>
      <imgPath><![CDATA[http://vimg3.ws.126.net/image/snapshot/2014/1/G/0/V9HB98QG0_120~90.jpg]]></imgPath>
      <pageUrl><![CDATA[http://v.mobile.163.com/video/2014/1/F/V/V9HB98QFV.html]]></pageUrl>
      <playLength>77</playLength>
      <source><![CDATA[网易]]></source>
      <title><![CDATA[佟掌柜砖机第二十一期 土曼科技]]></title>
      <videoId><![CDATA[V9HB98QFV]]></videoId>
    </item>
    <item>
      <hits>32</hits>
      <imgPath><![CDATA[http://vimg2.ws.126.net/image/snapshot/2014/1/0/8/V9HB73B08_120~90.jpg]]></imgPath>
      <pageUrl><![CDATA[http://v.mobile.163.com/video/2014/1/0/7/V9HB73B07.html]]></pageUrl>
      <playLength>172</playLength>
      <source><![CDATA[网易]]></source>
      <title><![CDATA[佟掌柜砖机第二十一期 乐心医疗]]></title>
      <videoId><![CDATA[V9HB73B07]]></videoId>
    </item>
    <item>
      <hits>31</hits>
      <imgPath><![CDATA[http://vimg2.ws.126.net/image/snapshot/2014/1/B/G/V9HB5RRBG_120~90.jpg]]></imgPath>
      <pageUrl><![CDATA[http://v.mobile.163.com/video/2014/1/B/F/V9HB5RRBF.html]]></pageUrl>
      <playLength>100</playLength>
      <source><![CDATA[网易]]></source>
      <title><![CDATA[佟掌柜砖机第二十一期 咕咚智能手环]]></title>
      <videoId><![CDATA[V9HB5RRBF]]></videoId>
    </item>
    <item>
      <hits>26</hits>
      <imgPath><![CDATA[http://vimg2.ws.126.net/image/snapshot/2014/1/4/U/V9HBA1G4U_120~90.jpg]]></imgPath>
      <pageUrl><![CDATA[http://v.mobile.163.com/video/2014/1/4/T/V9HBA1G4T.html]]></pageUrl>
      <playLength>56</playLength>
      <source><![CDATA[网易]]></source>
      <title><![CDATA[佟掌柜砖机第二十一期 蓝天航模]]></title>
      <videoId><![CDATA[V9HBA1G4T]]></videoId>
    </item>
    <item>
      <hits>17</hits>
      <imgPath><![CDATA[http://vimg1.ws.126.net/image/snapshot/2014/1/L/L/V9HB841LL_120~90.jpg]]></imgPath>
      <pageUrl><![CDATA[http://v.mobile.163.com/video/2014/1/L/K/V9HB841LK.html]]></pageUrl>
      <playLength>200</playLength>
      <source><![CDATA[网易]]></source>
      <title><![CDATA[佟掌柜砖机第二十一期 优美科技]]></title>
      <videoId><![CDATA[V9HB841LK]]></videoId>
    </item>
  </items>
  <size>16</size>
</document>
